Workbook

Sheet Sales Data
A1: Order ID | B1: Month | C1: Region | D1: Product | E1: Units Sold | F1: Unit Price | G1: Total Sales | H1: Profit Margin %
A2: 1001 | B2: Jan | C2: North | D2: Laptop | E2: 91 | F2: 1200 | G2: 109200 | H2: 0.22
A3: 1002 | B3: Jan | C3: North | D3: Smartphone | E3: 24 | F3: 800 | G3: 19200 | H3: 0.28
A4: 1003 | B4: Jan | C4: North | D4: Tablet | E4: 13 | F4: 500 | G4: 6500 | H4: 0.25
A5: 1004 | B5: Jan | C5: North | D5: Monitor | E5: 45 | F5: 350 | G5: 15750 | H5: 0.2
A6: 1005 | B6: Jan | C6: North | D6: Keyboard | E6: 41 | F6: 100 | G6: 4100 | H6: 0.35
A7: 1006 | B7: Jan | C7: South | D7: Laptop | E7: 38 | F7: 1200 | G7: 45600 | H7: 0.22
A8: 1007 | B8: Jan | C8: South | D8: Smartphone | E8: 27 | F8: 800 | G8: 21600 | H8: 0.28
A9: 1008 | B9: Jan | C9: South | D9: Tablet | E9: 23 | F9: 500 | G9: 11500 | H9: 0.25
A10: 1009 | B10: Jan | C10: South | D10: Monitor | E10: 96 | F10: 350 | G10: 33600 | H10: 0.2
A11: 1010 | B11: Jan | C11: South | D11: Keyboard | E11: 79 | F11: 100 | G11: 7900 | H11: 0.35
A12: 1011 | B12: Jan | C12: East | D12: Laptop | E12: 21 | F12: 1200 | G12: 25200 | H12: 0.22
A13: 1012 | B13: Jan | C13: East | D13: Smartphone | E13: 85 | F13: 800 | G13: 68000 | H13: 0.28
... A241: 1240 | B241: Dec | C241: West | D241: Keyboard | E241: 75 | F241: 100 | G241: 7500 | H241: 0.35

Sheet Summary
A1: Sales Performance Analysis – 2024
A3: Key Metrics
A4: Metric | B4: Value
A5: Total Revenue | B5: =SUM('Sales Data'!G:G)
A6: Total Units Sold | B6: =SUM('Sales Data'!E:E)
A7: Avg Profit Margin | B7: =AVERAGE('Sales Data'!H:H)
A8: Best Performing Product | B8: Laptop
A10: Monthly Sales Summary
A11: Month | B11: Total Sales ($) | C11: Units Sold
A12: Jan | B12: =SUMIF('Sales Data'!B:B,"Jan",'Sales Data'!G:G) | C12: =SUMIF('Sales Data'!B:B,"Jan",'Sales Data'!E:E)
A13: Feb | B13: =SUMIF('Sales Data'!B:B,"Feb",'Sales Data'!G:G) | C13: =SUMIF('Sales Data'!B:B,"Feb",'Sales Data'!E:E)
A14: Mar | B14: =SUMIF('Sales Data'!B:B,"Mar",'Sales Data'!G:G) | C14: =SUMIF('Sales Data'!B:B,"Mar",'Sales Data'!E:E)
A15: Apr | B15: =SUMIF('Sales Data'!B:B,"Apr",'Sales Data'!G:G) | C15: =SUMIF('Sales Data'!B:B,"Apr",'Sales Data'!E:E)
A16: May | B16: =SUMIF('Sales Data'!B:B,"May",'Sales Data'!G:G) | C16: =SUMIF('Sales Data'!B:B,"May",'Sales Data'!E:E)
A17: Jun | B17: =SUMIF('Sales Data'!B:B,"Jun",'Sales Data'!G:G) | C17: =SUMIF('Sales Data'!B:B,"Jun",'Sales Data'!E:E)
A18: Jul | B18: =SUMIF('Sales Data'!B:B,"Jul",'Sales Data'!G:G) | C18: =SUMIF('Sales Data'!B:B,"Jul",'Sales Data'!E:E)
A19: Aug | B19: =SUMIF('Sales Data'!B:B,"Aug",'Sales Data'!G:G) | C19: =SUMIF('Sales Data'!B:B,"Aug",'Sales Data'!E:E)
A20: Sep | B20: =SUMIF('Sales Data'!B:B,"Sep",'Sales Data'!G:G) | C20: =SUMIF('Sales Data'!B:B,"Sep",'Sales Data'!E:E)
A21: Oct | B21: =SUMIF('Sales Data'!B:B,"Oct",'Sales Data'!G:G) | C21: =SUMIF('Sales Data'!B:B,"Oct",'Sales Data'!E:E)
A22: Nov | B22: =SUMIF('Sales Data'!B:B,"Nov",'Sales Data'!G:G) | C22: =SUMIF('Sales Data'!B:B,"Nov",'Sales Data'!E:E)
A23: Dec | B23: =SUMIF('Sales Data'!B:B,"Dec",'Sales Data'!G:G) | C23: =SUMIF('Sales Data'!B:B,"Dec",'Sales Data'!E:E)
A26: Sales by Region
A27: Region | B27: Total Sales ($) | C27: Units Sold
A28: North | B28: =SUMIF('Sales Data'!C:C,"North",'Sales Data'!G:G) | C28: =SUMIF('Sales Data'!C:C,"North",'Sales Data'!E:E)
A29: South | B29: =SUMIF('Sales Data'!C:C,"South",'Sales Data'!G:G) | C29: =SUMIF('Sales Data'!C:C,"South",'Sales Data'!E:E)
A30: East | B30: =SUMIF('Sales Data'!C:C,"East",'Sales Data'!G:G) | C30: =SUMIF('Sales Data'!C:C,"East",'Sales Data'!E:E)
A31: West | B31: =SUMIF('Sales Data'!C:C,"West",'Sales Data'!G:G) | C31: =SUMIF('Sales Data'!C:C,"West",'Sales Data'!E:E)
A34: Sales by Product
A35: Product | B35: Total Sales ($) | C35: Units Sold
A36: Laptop | B36: =SUMIF('Sales Data'!D:D,"Laptop",'Sales Data'!G:G) | C36: =SUMIF('Sales Data'!D:D,"Laptop",'Sales Data'!E:E)
A37: Smartphone | B37: =SUMIF('Sales Data'!D:D,"Smartphone",'Sales Data'!G:G) | C37: =SUMIF('Sales Data'!D:D,"Smartphone",'Sales Data'!E:E)
A38: Tablet | B38: =SUMIF('Sales Data'!D:D,"Tablet",'Sales Data'!G:G) | C38: =SUMIF('Sales Data'!D:D,"Tablet",'Sales Data'!E:E)
A39: Monitor | B39: =SUMIF('Sales Data'!D:D,"Monitor",'Sales Data'!G:G) | C39: =SUMIF('Sales Data'!D:D,"Monitor",'Sales Data'!E:E)
A40: Keyboard | B40: =SUMIF('Sales Data'!D:D,"Keyboard",'Sales Data'!G:G) | C40: =SUMIF('Sales Data'!D:D,"Keyboard",'Sales Data'!E:E)
